godot_event/__init__.py
godot_event/core.py
godot_event/error_handling.py
godot_event/input_system.py
godot_event/pygame_integration.py
godot_event-0.1.1.dist-info/licenses/LICENSE
godot_event-0.1.1.dist-info/METADATA
godot_event-0.1.1.dist-info/WHEEL
godot_event-0.1.1.dist-info/top_level.txt
godot_event-0.1.1.dist-info/RECORD
