Metadata-Version: 2.4
Name: godot-event
Version: 0.1.1
Summary: Godot风格的事件系统工具库 - 支持Windows键盘所有按键、组合键和特殊键
Author-email: FriskYan <friskyan@example.com>
License: MIT License
Keywords: godot,event,input,keyboard,game,utilities
Classifier: Programming Language :: Python :: 3
Classifier: Programming Language :: Python :: 3 :: Only
Classifier: Programming Language :: Python :: 3.8
Classifier: Programming Language :: Python :: 3.9
Classifier: Programming Language :: Python :: 3.10
Classifier: Programming Language :: Python :: 3.11
Classifier: License :: OSI Approved :: MIT License
Classifier: Operating System :: OS Independent
Classifier: Operating System :: Microsoft :: Windows
Classifier: Operating System :: POSIX :: Linux
Classifier: Operating System :: MacOS
Classifier: Intended Audience :: Developers
Classifier: Topic :: Software Development :: Libraries
Classifier: Topic :: Games/Entertainment
Requires-Python: >=3.8
License-File: LICENSE
Provides-Extra: pygame
Requires-Dist: pygame>=2.0.0; extra == "pygame"
Dynamic: license-file
